{
"c643nx":[42,33600,0,"BigInt: OP_BOOLOR 1-byte number (all bits set) and 8-byte number (all bits set) (P2S)"],
"msfmuu":[42,33600,0,"BigInt: OP_BOOLOR 8-byte number (all bits set) and 1-byte number (all bits set) (P2S)"],
"znjrsd":[42,33600,0,"BigInt: OP_BOOLOR 8-byte number (all bits set) and 8-byte number (all bits set) (P2S)"],
"2d5kmc":[42,33600,0,"BigInt: OP_BOOLOR 1-byte number (alternating bits set) and 1-byte number (alternating bits set) (P2S)"],
"6qephz":[42,33600,0,"BigInt: OP_BOOLOR 1-byte number (alternating bits set) and 8-byte number (alternating bits set) (P2S)"],
"z9x39m":[42,33600,0,"BigInt: OP_BOOLOR 8-byte number (alternating bits set) and 1-byte number (alternating bits set) (P2S)"],
"9jx2yn":[42,33600,0,"BigInt: OP_BOOLOR 8-byte number (alternating bits set) and 8-byte number (alternating bits set) (P2S)"],
"w820mj":[42,33600,0,"BigInt: OP_BOOLOR 1-byte number (highest-bit set) and 1-byte number (highest-bit set) (P2S)"],
"klg5ee":[42,33600,0,"BigInt: OP_BOOLOR 1-byte number (highest-bit set) and 8-byte number (highest-bit set) (P2S)"],
"vkvemf":[42,33600,0,"BigInt: OP_BOOLOR 8-byte number (highest-bit set) and 1-byte number (highest-bit set) (P2S)"],
"hx4p0x":[42,33600,0,"BigInt: OP_BOOLOR 8-byte number (highest-bit set) and 8-byte number (highest-bit set) (P2S)"],
"mt9awv":[42,33600,0,"BigInt: OP_BOOLOR 8-byte number (one bit set per byte) and 1-byte number (one bit set per byte) (P2S)"],
"we2y0m":[42,33600,0,"BigInt: OP_BOOLOR 8-byte number (one bit set per byte) and 8-byte number (one bit set per byte) (P2S)"]
}